git_ext/__init__.py
git_ext/bitbucket.py
git_ext/git.py
git_ext/gitlab.py
git_ext/utils.py
git_ext/bin/__init__.py
git_ext/bin/gist.py
git_ext/bin/init_git_ext.py
git_ext/bin/pullrequest.py
git_ext/github/__init__.py
git_ext/github/gist.py
git_ext/static/CONFIG_TEMPLATE.yml
git_ext/static/PR_SUBMIT_TEMPLATE
git_ext-0.6.0.dist-info/METADATA
git_ext-0.6.0.dist-info/RECORD
git_ext-0.6.0.dist-info/WHEEL
git_ext-0.6.0.dist-info/entry_points.txt
git_ext-0.6.0.dist-info/top_level.txt
tests/__init__.py
tests/conftest.py
tests/test_git.py
tests/test_pullrequest.py
tests/test_utils.py
