Metadata-Version: 2.1
Name: git-ext
Version: 0.6.0
Summary: A git extension that allows you submit pullrequests from command line.
Home-page: https://github.com/laixintao/git-ext
Author: laixintao
Author-email: laixintao1995@163.com
License: GNU
Platform: UNKNOWN
Requires-Dist: arrow (>=0.10.0)
Requires-Dist: click (>=6.7)
Requires-Dist: PyYAML (>=3.12)
Requires-Dist: requests (>=2.18.1)
Requires-Dist: six (>=1.11.0)
